{
  "welcome": "Bienvenido a React",
  "login": "Iniciar sesión",
  "logout": "Cerrar sesión",
  "title": "HydroSensor-Track",
  "dashboard": "Dashboard",
  "tickets": "Tickets",
  "notifications": "Notificaciones",
  "backoffice": "Backoffice",
  "settings": "Configuración",
  "homeTitle": "Pagina principal",
  "filters": "Filtros",
  "location": "Ubicación",
  "brand": "Modelo",
  "model": "Modelo",
  "level": "Nivel",
  "battery": "Batería",
  "signal": "Señal",
  "hour": "Hora",
  "latitude": "Latitud",
  "longitude": "Longitud",
  "sensorId": "ID del sensor",
  "createGraph": "Crear gráfico",
  "downloadReport": "Descargar reporte",
  "search": "Buscar",
  "addNewUser": "Agregar nuevo usuario",
  "cancel": "Cancelar",
  "save": "Guardar",
  "enterEmail": "Ingrese su correo electrónico",
  "enterUserName": "Ingrese su nombre de usuario",
  "enterPassword": "Ingrese su contraseña",
  "enterFirstName": "Ingrese su nombre",
  "enterLastName": "Ingrese su apellido",
  "emailHeader": "Correo electrónico",
  "userNameHeader": "Nombre de usuario",
  "passwordHeader": "Contraseña",
  "firstNameHeader": "Nombre",
  "lastNameHeader": "Apellido",
  "invalidUserName": "El nombre de usuario debe tener al entre 3 y 15 caracteres, solo puede contener letras, números, guiones y guiones bajos.",
  "invalidPassword": "La contraseña debe tener al menos 8 caracteres.",
  "invalidEmail": "El correo electrónico no es válido.",
  "userProfile": "Perfil de usuario",
  "changePassword": "Cambiar contraseña",
  "modify": "Modificar",
  "differentInput": "El nuevo valor debe ser diferente al actual.",
  "fieldDoesNotEmpty": "El campo no puede estar vacío.",
  "confirmPasswordHeader": "Confirme su contraseña",
  "passwordsDoNotMatch": "Las contraseñas no coinciden.",
  "emailVerified": "Correo electrónico verificado",
  "emailNotVerified": "Correo electrónico no verificado",
  "lastLoginHeader": "Última sesión",
  "lastPasswordResetHeader": "Último restablecimiento de contraseña",
  "updatedAtHeader": "Actualizado en",
  "createdAtHeader": "Creado en",
  "noData": "Sin datos",
  "verified": "Verificado"
}